gekko/ML.py
gekko/__init__.py
gekko/apm.py
gekko/brain.py
gekko/chemical.py
gekko/gekko.py
gekko/gk_debug.py
gekko/gk_global_options.py
gekko/gk_gui.py
gekko/gk_operators.py
gekko/gk_parameter.py
gekko/gk_post_solve.py
gekko/gk_solver_extension.py
gekko/gk_solver_extension_amplpy.py
gekko/gk_solver_extension_pyomo.py
gekko/gk_variable.py
gekko/gk_write_files.py
gekko/properties.py
gekko/support.py
gekko/bin/apm
gekko/bin/apm.exe
gekko/bin/apm_aarch64
gekko/bin/apm_arm
gekko/bin/apm_mac
gekko/static/index.html
gekko/static/static/GekkoLogo.png
gekko/static/static/bootstrap.min.css
gekko/static/static/css/app.c68ba9dcf7bd08c3aad2e946c455bc61.css
gekko/static/static/css/app.c68ba9dcf7bd08c3aad2e946c455bc61.css.map
gekko/static/static/js/app.943e6331e1599b12b7df.js
gekko/static/static/js/app.943e6331e1599b12b7df.js.map
gekko/static/static/js/manifest.13b220bf0bb1548816a4.js
gekko/static/static/js/manifest.13b220bf0bb1548816a4.js.map
gekko/static/static/js/vendor.0ec4a591b473bfdae464.js
gekko/static/static/js/vendor.0ec4a591b473bfdae464.js.map
gekko-1.3.1.dist-info/LICENSE
gekko-1.3.1.dist-info/METADATA
gekko-1.3.1.dist-info/WHEEL
gekko-1.3.1.dist-info/top_level.txt
gekko-1.3.1.dist-info/RECORD
