Metadata-Version: 2.1
Name: gekko
Version: 1.3.1
Summary: Machine learning and optimization for dynamic systems
Home-page: https://github.com/BYU-PRISM/GEKKO
Author: BYU PRISM Lab
Author-email: support@apmonitor.com
License: MIT
Keywords: differential deep learning solver equations optimization mixed-integer
Classifier: Development Status :: 5 - Production/Stable
Classifier: Programming Language :: Python :: 2
Classifier: Programming Language :: Python :: 2.7
Classifier: Programming Language :: Python :: 3
Classifier: Programming Language :: Python :: 3.4
Classifier: Programming Language :: Python :: 3.5
Classifier: Programming Language :: Python :: 3.6
Classifier: Programming Language :: Python :: 3.7
Classifier: Programming Language :: Python :: 3.8
Classifier: Programming Language :: Python :: 3.9
Classifier: Programming Language :: Python :: 3.10
Classifier: Programming Language :: Python :: 3.11
Classifier: Programming Language :: Python :: 3.12
Classifier: Programming Language :: Python :: 3.13
Classifier: Programming Language :: Python :: 3.14
Requires-Python: >=2.6
License-File: LICENSE
Requires-Dist: numpy>=1.8
